Metadata-Version: 2.1
Name: somtimes
Version: 1.0.1
Summary: Python implementation of SOMTimeS: Self Organizing Map for Time Series
Home-page: https://github.com/ali-javed/somtimes
Author: A. Javed
Author-email: alijaved@live.com
License: UNKNOWN
Download-URL: https://github.com/ali-javed/somtimes/archive/refs/tags/1.0.1.tar.gz
Platform: UNKNOWN
License-File: LICENSE.md
